CHANGES.rst
CONTRIBUTORS.rst
MANIFEST.in
README.rst
setup.py
docs/LICENSE.GPL
docs/LICENSE.txt
src/interlegis/__init__.py
src/interlegis.portalmodelo.ombudsman.egg-info/PKG-INFO
src/interlegis.portalmodelo.ombudsman.egg-info/SOURCES.txt
src/interlegis.portalmodelo.ombudsman.egg-info/dependency_links.txt
src/interlegis.portalmodelo.ombudsman.egg-info/namespace_packages.txt
src/interlegis.portalmodelo.ombudsman.egg-info/not-zip-safe
src/interlegis.portalmodelo.ombudsman.egg-info/requires.txt
src/interlegis.portalmodelo.ombudsman.egg-info/top_level.txt
src/interlegis/portalmodelo/__init__.py
src/interlegis/portalmodelo/ombudsman/__init__.py
src/interlegis/portalmodelo/ombudsman/adapters.py
src/interlegis/portalmodelo/ombudsman/behaviors.py
src/interlegis/portalmodelo/ombudsman/config.py
src/interlegis/portalmodelo/ombudsman/configure.zcml
src/interlegis/portalmodelo/ombudsman/profiles.zcml
src/interlegis/portalmodelo/ombudsman/setuphandlers.py
src/interlegis/portalmodelo/ombudsman/subscribers.py
src/interlegis/portalmodelo/ombudsman/testing.py
src/interlegis/portalmodelo/ombudsman/vocabulary.py
src/interlegis/portalmodelo/ombudsman/browser/__init__.py
src/interlegis/portalmodelo/ombudsman/browser/claim.py
src/interlegis/portalmodelo/ombudsman/browser/claims_by_date.py
src/interlegis/portalmodelo/ombudsman/browser/claims_by_kind.py
src/interlegis/portalmodelo/ombudsman/browser/claims_by_state.py
src/interlegis/portalmodelo/ombudsman/browser/claims_by_tag.py
src/interlegis/portalmodelo/ombudsman/browser/claims_util.py
src/interlegis/portalmodelo/ombudsman/browser/configure.zcml
src/interlegis/portalmodelo/ombudsman/browser/json_api.py
src/interlegis/portalmodelo/ombudsman/browser/notifications.py
src/interlegis/portalmodelo/ombudsman/browser/ombudsoffice.py
src/interlegis/portalmodelo/ombudsman/browser/response.py
src/interlegis/portalmodelo/ombudsman/browser/validator.py
src/interlegis/portalmodelo/ombudsman/browser/templates/claim_view.pt
src/interlegis/portalmodelo/ombudsman/browser/templates/ombudsoffice_view.pt
src/interlegis/portalmodelo/ombudsman/content/__init__.py
src/interlegis/portalmodelo/ombudsman/content/claim.py
src/interlegis/portalmodelo/ombudsman/content/ombudsoffice.py
src/interlegis/portalmodelo/ombudsman/interfaces/__init__.py
src/interlegis/portalmodelo/ombudsman/interfaces/claim.py
src/interlegis/portalmodelo/ombudsman/interfaces/ombudsoffice.py
