Metadata-Version: 2.1
Name: interlegis.portalmodelo.ombudsman
Version: 1.7
Summary: Sistema de Ouvidoria do Portal Modelo do Interlegis.
Home-page: https://github.com/interlegis/interlegis.portalmodelo.ombudsman
Author: Programa Interlegis
Author-email: ti@interlegis.leg.br
License: UNKNOWN
Keywords: interlegis transparency portalmodelo
Platform: UNKNOWN
Classifier: Development Status :: 5 - Production/Stable
Classifier: Environment :: Web Environment
Classifier: Framework :: Plone
Classifier: Framework :: Plone :: 4.3
Classifier: Intended Audience :: System Administrators
Classifier: License :: OSI Approved :: GNU General Public License v2 (GPLv2)
Classifier: Operating System :: OS Independent
Classifier: Programming Language :: Python
Classifier: Programming Language :: Python :: 2.7
Classifier: Topic :: Software Development :: Libraries :: Python Modules
Provides-Extra: test
